llmmerge/__init__.py
llmmerge/core.py
llmmerge/driver.py
llmmerge-0.2.2.dist-info/METADATA
llmmerge-0.2.2.dist-info/WHEEL
llmmerge-0.2.2.dist-info/entry_points.txt
llmmerge-0.2.2.dist-info/top_level.txt
llmmerge-0.2.2.dist-info/RECORD
