Metadata-Version: 2.4
Name: llmmerge
Version: 0.2.2
Summary: A custom LLM-based git merge driver.
Author-email: Abhishek Agarwal <ultimateabhi@gmail.com>
Requires-Python: >=3.10
